napalm_huawei_vrp/__init__.py
napalm_huawei_vrp/huawei_vrp.py
napalm_huawei_vrp/utils/__init__.py
napalm_huawei_vrp/utils/utils.py
napalm_huawei_vrp-1.2.0.dist-info/AUTHORS
napalm_huawei_vrp-1.2.0.dist-info/LICENSE
napalm_huawei_vrp-1.2.0.dist-info/METADATA
napalm_huawei_vrp-1.2.0.dist-info/WHEEL
napalm_huawei_vrp-1.2.0.dist-info/entry_points.txt
napalm_huawei_vrp-1.2.0.dist-info/top_level.txt
napalm_huawei_vrp-1.2.0.dist-info/RECORD
