Metadata-Version: 2.1
Name: napalm-huawei-vrp
Version: 1.2.0
Summary: Network Automation and Programmability Abstraction Layer with Multi-vendor support,Driver for VRP OS
Home-page: https://github.com/napalm-automation-community/napalm-huawei-vrp
Author: Locus Li, Michael Alvarez
Author-email: locus@byto.top, codingnetworks@gmail.com
License: Apache 2.0
Classifier: Topic :: Utilities
Classifier: License :: OSI Approved :: Apache Software License
Classifier: Programming Language :: Python
Classifier: Programming Language :: Python :: 3
Classifier: Programming Language :: Python :: 3.6
Classifier: Programming Language :: Python :: 3.7
Classifier: Programming Language :: Python :: 3.8
Classifier: Programming Language :: Python :: 3.9
Classifier: Operating System :: POSIX :: Linux
Classifier: Operating System :: MacOS
License-File: LICENSE
License-File: AUTHORS
Requires-Dist: napalm>=3.0.0
Requires-Dist: diffplus
